{
    "database_id": 919,
    "label": "ZW15RM-PLUS",
    "manufacturer_name": "Wenzhou MTLC Electric Appliances Co.,Ltd.",
    "manufacturer_id": "011A",
    "device_ref": [
        "0111:0105"
    ],
    "version_min": 0,
    "version_max": 255.255,
    "decription": "In-Wall Smart Meter Duplex Receptacle (15A)",
    "overview": "<p>Z-Wave Tamper Resistant Duplex Receptacle that monitors power and allows for Z-Wave control of the \"bottom\" outlet. The outlet is rated for 120VAC, 15A.<\/p>",
    "inclusion": "<ol><li>Active \"Inclusion Mode\" on your controller.<\/li> <li>Press and hold the manual ON\/OFF button on the receptacle for around 3 seconds.<\/li> <li>The primary controller will indicate the inclusion is successful.<\/li> <\/ol>",
    "exclusion": "<ol><li>Active \"Exclusion Mode\" on your controller.<\/li> <li>Press and hold the manual ON\/OFF button for 3 seconds.<\/li> <li>The blue LED indicator will blink, indicating exclusion was successful.<\/li> <\/ol>",
    "wakeup": "",
    "protocol_version": 4.024,
    "listening": true,
    "frequently_listening": false,
    "routing": true,
    "beaming": true,
    "library_type": {
        "id": 6,
        "name": "LIB_SLAVE_ROUTING"
    },
    "basic_class": {
        "id": 4,
        "name": "BASIC_TYPE_ROUTING_SLAVE"
    },
    "generic_class": {
        "id": 4,
        "name": "GENERIC_TYPE_SWITCH_BINARY"
    },
    "specific_class": {
        "id": 4,
        "name": "SPECIFIC_TYPE_POWER_SWITCH_BINARY"
    },
    "endpoints": [
        {
            "id": 0,
            "basic_class": {
                "id": 4,
                "name": "BASIC_TYPE_ROUTING_SLAVE"
            },
            "generic_class": {
                "id": 16,
                "name": "GENERIC_TYPE_SWITCH_BINARY"
            },
            "specific_class": {
                "id": 1,
                "name": "SPECIFIC_TYPE_POWER_SWITCH_BINARY"
            },
            "commandclasses": [
                {
                    "id": "00",
                    "name": "NO_OPERATION",
                    "version": "1",
                    "nif": false,
                    "basic": false,
                    "secure": false,
                    "nonsecure": true,
                    "config": "",
                    "channels": []
                },
                {
                    "id": "20",
                    "name": "BASIC",
                    "version": "1",
                    "nif": false,
                    "basic": false,
                    "secure": false,
                    "nonsecure": true,
                    "config": "",
                    "channels": []
                },
                {
                    "id": "25",
                    "name": "SWITCH_BINARY",
                    "version": "1",
                    "nif": true,
                    "basic": true,
                    "secure": false,
                    "nonsecure": true,
                    "config": "",
                    "channels": [
                        {
                            "type": "switch_binary",
                            "label": "Switch",
                            "config": []
                        }
                    ]
                },
                {
                    "id": "27",
                    "name": "SWITCH_ALL",
                    "version": "1",
                    "nif": true,
                    "basic": false,
                    "secure": false,
                    "nonsecure": true,
                    "config": "",
                    "channels": []
                },
                {
                    "id": "32",
                    "name": "METER",
                    "version": "3",
                    "nif": true,
                    "basic": false,
                    "secure": false,
                    "nonsecure": true,
                    "config": "",
                    "channels": [
                        {
                            "type": "meter_kwh",
                            "label": "Electric meter (kWh)",
                            "config": [
                                "type=E_KWh"
                            ]
                        },
                        {
                            "type": "meter_watts",
                            "label": "Electric meter (watts)",
                            "config": [
                                "type=E_W"
                            ]
                        }
                    ]
                },
                {
                    "id": "59",
                    "name": "ASSOCIATION_GROUP_INFO",
                    "version": "1",
                    "nif": true,
                    "basic": false,
                    "secure": false,
                    "nonsecure": true,
                    "config": "",
                    "channels": []
                },
                {
                    "id": "5A",
                    "name": "DEVICE_RESET_LOCALLY",
                    "version": "1",
                    "nif": true,
                    "basic": false,
                    "secure": false,
                    "nonsecure": true,
                    "config": "",
                    "channels": []
                },
                {
                    "id": "5E",
                    "name": "ZWAVE_PLUS_INFO",
                    "version": "1",
                    "nif": true,
                    "basic": false,
                    "secure": false,
                    "nonsecure": true,
                    "config": "",
                    "channels": []
                },
                {
                    "id": "70",
                    "name": "CONFIGURATION",
                    "version": "1",
                    "nif": true,
                    "basic": false,
                    "secure": false,
                    "nonsecure": true,
                    "config": "",
                    "channels": []
                },
                {
                    "id": "72",
                    "name": "MANUFACTURER_SPECIFIC",
                    "version": "1",
                    "nif": true,
                    "basic": false,
                    "secure": false,
                    "nonsecure": true,
                    "config": "",
                    "channels": []
                },
                {
                    "id": "73",
                    "name": "POWERLEVEL",
                    "version": "1",
                    "nif": true,
                    "basic": false,
                    "secure": false,
                    "nonsecure": true,
                    "config": "",
                    "channels": []
                },
                {
                    "id": "85",
                    "name": "ASSOCIATION",
                    "version": "2",
                    "nif": true,
                    "basic": false,
                    "secure": false,
                    "nonsecure": true,
                    "config": "",
                    "channels": []
                },
                {
                    "id": "86",
                    "name": "VERSION",
                    "version": "2",
                    "nif": true,
                    "basic": false,
                    "secure": false,
                    "nonsecure": true,
                    "config": "",
                    "channels": []
                }
            ]
        }
    ],
    "parameters": [
        {
            "id": 1,
            "label": "ON\/OFF",
            "description": "Synchronization of outlet power and LED indicator",
            "overview": "<p>\u00a0This value only controls the bottom outlet, the top outlet is always on.<\/p>",
            "size": 1,
            "bitmask": "00000000",
            "default": 0,
            "read_only": false,
            "write_only": false,
            "value_min": 0,
            "value_max": 1,
            "options": [
                {
                    "value": 0,
                    "label": "Power on, LED off"
                },
                {
                    "value": 1,
                    "label": "Power on, LED on"
                }
            ]
        }
    ],
    "associations": [
        {
            "id": 1,
            "label": "Lifeline",
            "max_nodes": 1,
            "controller": true,
            "description": "Send device reset local notification",
            "overview": ""
        },
        {
            "id": 2,
            "label": "StatusReport",
            "max_nodes": 5,
            "controller": false,
            "description": "Send basic report",
            "overview": ""
        },
        {
            "id": 3,
            "label": "PowerReport",
            "max_nodes": 5,
            "controller": false,
            "description": "Send meter power report",
            "overview": ""
        }
    ]
}