{
    "database_id": 666,
    "label": "DL9101V",
    "manufacturer_name": "Shenzhen iSurpass Technology Co. ,Ltd",
    "manufacturer_id": "021C",
    "device_ref": [
        "5000:1000"
    ],
    "version_min": 0,
    "version_max": 255.255,
    "decription": "Door Lock with Handle",
    "overview": "",
    "inclusion": "",
    "exclusion": "",
    "wakeup": "",
    "protocol_version": 0,
    "listening": false,
    "frequently_listening": true,
    "routing": true,
    "beaming": true,
    "library_type": {
        "id": 0,
        "name": "Unknown"
    },
    "basic_class": {
        "id": 4,
        "name": "BASIC_TYPE_ROUTING_SLAVE"
    },
    "generic_class": {
        "id": 4,
        "name": "GENERIC_TYPE_ENTRY_CONTROL"
    },
    "specific_class": {
        "id": 4,
        "name": "SPECIFIC_TYPE_SECURE_DOOR"
    },
    "endpoints": [
        {
            "id": 0,
            "basic_class": {
                "id": 4,
                "name": "BASIC_TYPE_ROUTING_SLAVE"
            },
            "generic_class": {
                "id": 64,
                "name": "GENERIC_TYPE_ENTRY_CONTROL"
            },
            "specific_class": {
                "id": 5,
                "name": "SPECIFIC_TYPE_SECURE_DOOR"
            },
            "commandclasses": [
                {
                    "id": "00",
                    "name": "NO_OPERATION",
                    "version": "1",
                    "nif": true,
                    "basic": false,
                    "secure": false,
                    "nonsecure": true,
                    "config": "",
                    "channels": []
                },
                {
                    "id": "25",
                    "name": "SWITCH_BINARY",
                    "version": "1",
                    "nif": true,
                    "basic": false,
                    "secure": false,
                    "nonsecure": true,
                    "config": "",
                    "channels": [
                        {
                            "type": "switch_binary",
                            "label": "Switch",
                            "config": []
                        }
                    ]
                },
                {
                    "id": "4C",
                    "name": "DOOR_LOCK_LOGGING",
                    "version": "1",
                    "nif": true,
                    "basic": false,
                    "secure": false,
                    "nonsecure": true,
                    "config": "",
                    "channels": []
                },
                {
                    "id": "4E",
                    "name": "SCHEDULE_ENTRY_LOCK",
                    "version": "1",
                    "nif": true,
                    "basic": false,
                    "secure": false,
                    "nonsecure": true,
                    "config": "",
                    "channels": []
                },
                {
                    "id": "59",
                    "name": "ASSOCIATION_GROUP_INFO",
                    "version": "1",
                    "nif": true,
                    "basic": false,
                    "secure": false,
                    "nonsecure": true,
                    "config": "",
                    "channels": []
                },
                {
                    "id": "5A",
                    "name": "DEVICE_RESET_LOCALLY",
                    "version": "1",
                    "nif": true,
                    "basic": false,
                    "secure": false,
                    "nonsecure": true,
                    "config": "",
                    "channels": []
                },
                {
                    "id": "5E",
                    "name": "ZWAVE_PLUS_INFO",
                    "version": "1",
                    "nif": true,
                    "basic": false,
                    "secure": false,
                    "nonsecure": true,
                    "config": "",
                    "channels": []
                },
                {
                    "id": "62",
                    "name": "DOOR_LOCK",
                    "version": "1",
                    "nif": true,
                    "basic": false,
                    "secure": false,
                    "nonsecure": true,
                    "config": "",
                    "channels": [
                        {
                            "type": "lock_door",
                            "label": "Door Lock",
                            "config": []
                        }
                    ]
                },
                {
                    "id": "63",
                    "name": "USER_CODE",
                    "version": "1",
                    "nif": true,
                    "basic": false,
                    "secure": false,
                    "nonsecure": true,
                    "config": "",
                    "channels": []
                },
                {
                    "id": "70",
                    "name": "CONFIGURATION",
                    "version": "1",
                    "nif": true,
                    "basic": false,
                    "secure": false,
                    "nonsecure": true,
                    "config": "",
                    "channels": []
                },
                {
                    "id": "71",
                    "name": "ALARM",
                    "version": "1",
                    "nif": true,
                    "basic": false,
                    "secure": false,
                    "nonsecure": true,
                    "config": "",
                    "channels": [
                        {
                            "type": "alarm_general",
                            "label": "Alarm",
                            "config": []
                        }
                    ]
                },
                {
                    "id": "72",
                    "name": "MANUFACTURER_SPECIFIC",
                    "version": "1",
                    "nif": true,
                    "basic": false,
                    "secure": false,
                    "nonsecure": true,
                    "config": "",
                    "channels": []
                },
                {
                    "id": "73",
                    "name": "POWERLEVEL",
                    "version": "1",
                    "nif": true,
                    "basic": false,
                    "secure": false,
                    "nonsecure": true,
                    "config": "",
                    "channels": []
                },
                {
                    "id": "77",
                    "name": "NODE_NAMING",
                    "version": "1",
                    "nif": true,
                    "basic": false,
                    "secure": false,
                    "nonsecure": true,
                    "config": "",
                    "channels": []
                },
                {
                    "id": "80",
                    "name": "BATTERY",
                    "version": "1",
                    "nif": true,
                    "basic": false,
                    "secure": false,
                    "nonsecure": true,
                    "config": "",
                    "channels": []
                },
                {
                    "id": "85",
                    "name": "ASSOCIATION",
                    "version": "2",
                    "nif": true,
                    "basic": false,
                    "secure": false,
                    "nonsecure": true,
                    "config": "",
                    "channels": []
                },
                {
                    "id": "86",
                    "name": "VERSION",
                    "version": "2",
                    "nif": true,
                    "basic": false,
                    "secure": false,
                    "nonsecure": true,
                    "config": "",
                    "channels": []
                },
                {
                    "id": "8B",
                    "name": "TIME_PARAMETERS",
                    "version": "1",
                    "nif": true,
                    "basic": false,
                    "secure": false,
                    "nonsecure": true,
                    "config": "",
                    "channels": [
                        {
                            "type": "time_offset",
                            "label": "Clock Time Offset",
                            "config": []
                        }
                    ]
                },
                {
                    "id": "98",
                    "name": "SECURITY",
                    "version": "1",
                    "nif": true,
                    "basic": false,
                    "secure": false,
                    "nonsecure": true,
                    "config": "",
                    "channels": []
                }
            ]
        }
    ],
    "parameters": [],
    "associations": [
        {
            "id": 1,
            "label": "Lifeline",
            "max_nodes": 5,
            "controller": true,
            "description": "",
            "overview": ""
        }
    ]
}