{
    "database_id": 943,
    "label": "Ring",
    "manufacturer_name": "Ring",
    "manufacturer_id": "0346",
    "device_ref": [
        "0301:0201"
    ],
    "version_min": 0,
    "version_max": 255.255,
    "decription": "Motion Sensor",
    "overview": "<p>Ring Alarm Motion Sensor: Expand your Ring Alarm system to secure each\u00a0room in your home, and get alerts as soon as they detect motion.<\/p>",
    "inclusion": "<ol><li>Activate inclusion mode on controller<\/li> <li>Pull tab\/quickly disconnect and reconnect battery<\/li> <li>Device should appear in Inbox<\/li> <\/ol>",
    "exclusion": "<ol><li>Initiate exclusion mode on controller<\/li> <li>Open contact sensor\u2019s cover Remove and replace battery quickly<\/li> <\/ol><p>Reset:<\/p> <ol><li>Press and hold the reset button found under the pinhole on the back of the device.<\/li> <li>The LED of the sensor should begin blinking. Hold the\u00a0 button down until the blinking stops<\/li> <li>Remove the cover from your motion sensor.<\/li> <li>Remove the battery.<\/li> <li>Place the battery back in the device.<\/li> <li>Put the cover back on the device.\u00a0<\/li> <\/ol>",
    "wakeup": "<p>By opening the cover, the sensor will get to tamper state and stay awake.<\/p>",
    "protocol_version": 6.001,
    "listening": false,
    "frequently_listening": false,
    "routing": true,
    "beaming": true,
    "library_type": {
        "id": 3,
        "name": "LIB_SLAVE_ENHANCED"
    },
    "basic_class": {
        "id": 4,
        "name": "BASIC_TYPE_ROUTING_SLAVE"
    },
    "generic_class": {
        "id": 4,
        "name": "GENERIC_TYPE_SENSOR_NOTIFICATION"
    },
    "specific_class": {
        "id": 4,
        "name": "SPECIFIC_TYPE_NOTIFICATION_SENSOR"
    },
    "endpoints": [
        {
            "id": 0,
            "basic_class": {
                "id": 4,
                "name": "BASIC_TYPE_ROUTING_SLAVE"
            },
            "generic_class": {
                "id": 7,
                "name": "GENERIC_TYPE_SENSOR_NOTIFICATION"
            },
            "specific_class": {
                "id": 1,
                "name": "SPECIFIC_TYPE_NOTIFICATION_SENSOR"
            },
            "commandclasses": [
                {
                    "id": "00",
                    "name": "NO_OPERATION",
                    "version": "1",
                    "nif": false,
                    "basic": false,
                    "secure": false,
                    "nonsecure": true,
                    "config": "",
                    "channels": []
                },
                {
                    "id": "20",
                    "name": "BASIC",
                    "version": "1",
                    "nif": false,
                    "basic": false,
                    "secure": false,
                    "nonsecure": true,
                    "config": "",
                    "channels": []
                },
                {
                    "id": "23",
                    "name": "ZIP_SERVICES",
                    "version": "0",
                    "nif": false,
                    "basic": false,
                    "secure": false,
                    "nonsecure": false,
                    "config": "",
                    "channels": []
                },
                {
                    "id": "30",
                    "name": "SENSOR_BINARY",
                    "version": "0",
                    "nif": false,
                    "basic": true,
                    "secure": false,
                    "nonsecure": false,
                    "config": "",
                    "channels": [
                        {
                            "type": "sensor_binary",
                            "label": "Binary Sensor",
                            "config": []
                        }
                    ]
                },
                {
                    "id": "59",
                    "name": "ASSOCIATION_GROUP_INFO",
                    "version": "1",
                    "nif": true,
                    "basic": false,
                    "secure": false,
                    "nonsecure": true,
                    "config": "",
                    "channels": []
                },
                {
                    "id": "5A",
                    "name": "DEVICE_RESET_LOCALLY",
                    "version": "1",
                    "nif": true,
                    "basic": false,
                    "secure": false,
                    "nonsecure": true,
                    "config": "",
                    "channels": []
                },
                {
                    "id": "5E",
                    "name": "ZWAVE_PLUS_INFO",
                    "version": "1",
                    "nif": true,
                    "basic": false,
                    "secure": false,
                    "nonsecure": true,
                    "config": "",
                    "channels": []
                },
                {
                    "id": "70",
                    "name": "CONFIGURATION",
                    "version": "1",
                    "nif": true,
                    "basic": false,
                    "secure": false,
                    "nonsecure": true,
                    "config": "",
                    "channels": []
                },
                {
                    "id": "71",
                    "name": "ALARM",
                    "version": "8",
                    "nif": true,
                    "basic": false,
                    "secure": false,
                    "nonsecure": true,
                    "config": "",
                    "channels": [
                        {
                            "type": "alarm_burglar",
                            "label": "Alarm (burglar)",
                            "config": [
                                "type=BURGLAR"
                            ]
                        }
                    ]
                },
                {
                    "id": "72",
                    "name": "MANUFACTURER_SPECIFIC",
                    "version": "1",
                    "nif": true,
                    "basic": false,
                    "secure": false,
                    "nonsecure": true,
                    "config": "",
                    "channels": []
                },
                {
                    "id": "73",
                    "name": "POWERLEVEL",
                    "version": "1",
                    "nif": true,
                    "basic": false,
                    "secure": false,
                    "nonsecure": true,
                    "config": "",
                    "channels": []
                },
                {
                    "id": "7A",
                    "name": "FIRMWARE_UPDATE_MD",
                    "version": "1",
                    "nif": true,
                    "basic": false,
                    "secure": false,
                    "nonsecure": true,
                    "config": "",
                    "channels": []
                },
                {
                    "id": "80",
                    "name": "BATTERY",
                    "version": "1",
                    "nif": true,
                    "basic": false,
                    "secure": false,
                    "nonsecure": true,
                    "config": "",
                    "channels": []
                },
                {
                    "id": "84",
                    "name": "WAKE_UP",
                    "version": "2",
                    "nif": true,
                    "basic": false,
                    "secure": false,
                    "nonsecure": true,
                    "config": "",
                    "channels": []
                },
                {
                    "id": "85",
                    "name": "ASSOCIATION",
                    "version": "2",
                    "nif": true,
                    "basic": false,
                    "secure": false,
                    "nonsecure": true,
                    "config": "",
                    "channels": []
                },
                {
                    "id": "86",
                    "name": "VERSION",
                    "version": "2",
                    "nif": true,
                    "basic": false,
                    "secure": false,
                    "nonsecure": true,
                    "config": "",
                    "channels": []
                },
                {
                    "id": "F0",
                    "name": "NON_INTEROPERABLE",
                    "version": "0",
                    "nif": false,
                    "basic": false,
                    "secure": false,
                    "nonsecure": false,
                    "config": "",
                    "channels": []
                }
            ]
        }
    ],
    "parameters": [],
    "associations": [
        {
            "id": 1,
            "label": "Lifeline",
            "max_nodes": 1,
            "controller": true,
            "description": "Controller Updates",
            "overview": ""
        },
        {
            "id": 2,
            "label": "Basic Report",
            "max_nodes": 1,
            "controller": false,
            "description": "Basic Report",
            "overview": "<p>Basic Report<\/p>"
        }
    ]
}