{
    "database_id": 301,
    "label": "ZM1701",
    "manufacturer_name": "Vision Security",
    "manufacturer_id": "0109",
    "device_ref": [
        "2006:0621"
    ],
    "version_min": 0,
    "version_max": 255.255,
    "decription": "Monoprice keypad door lock",
    "overview": "<p>Device is OEMed as Monoprice 10798.<\/p>",
    "inclusion": "",
    "exclusion": "",
    "wakeup": "",
    "protocol_version": 0,
    "listening": false,
    "frequently_listening": true,
    "routing": true,
    "beaming": true,
    "library_type": {
        "id": 0,
        "name": "Unknown"
    },
    "basic_class": {
        "id": 4,
        "name": "BASIC_TYPE_ROUTING_SLAVE"
    },
    "generic_class": {
        "id": 4,
        "name": "GENERIC_TYPE_ENTRY_CONTROL"
    },
    "specific_class": {
        "id": 4,
        "name": "SPECIFIC_TYPE_SECURE_KEYPAD_DOOR_LOCK"
    },
    "endpoints": [
        {
            "id": 0,
            "basic_class": {
                "id": 4,
                "name": "BASIC_TYPE_ROUTING_SLAVE"
            },
            "generic_class": {
                "id": 64,
                "name": "GENERIC_TYPE_ENTRY_CONTROL"
            },
            "specific_class": {
                "id": 3,
                "name": "SPECIFIC_TYPE_SECURE_KEYPAD_DOOR_LOCK"
            },
            "commandclasses": [
                {
                    "id": "00",
                    "name": "NO_OPERATION",
                    "version": "1",
                    "nif": false,
                    "basic": false,
                    "secure": false,
                    "nonsecure": true,
                    "config": "",
                    "channels": []
                },
                {
                    "id": "20",
                    "name": "BASIC",
                    "version": "1",
                    "nif": false,
                    "basic": false,
                    "secure": false,
                    "nonsecure": true,
                    "config": "",
                    "channels": []
                },
                {
                    "id": "4C",
                    "name": "DOOR_LOCK_LOGGING",
                    "version": "1",
                    "nif": false,
                    "basic": false,
                    "secure": false,
                    "nonsecure": false,
                    "config": "",
                    "channels": []
                },
                {
                    "id": "4E",
                    "name": "SCHEDULE_ENTRY_LOCK",
                    "version": "1",
                    "nif": false,
                    "basic": false,
                    "secure": false,
                    "nonsecure": false,
                    "config": "",
                    "channels": []
                },
                {
                    "id": "62",
                    "name": "DOOR_LOCK",
                    "version": "1",
                    "nif": false,
                    "basic": false,
                    "secure": false,
                    "nonsecure": false,
                    "config": "",
                    "channels": [
                        {
                            "type": "lock_door",
                            "label": "Door Lock",
                            "config": []
                        }
                    ]
                },
                {
                    "id": "63",
                    "name": "USER_CODE",
                    "version": "1",
                    "nif": false,
                    "basic": false,
                    "secure": false,
                    "nonsecure": false,
                    "config": "",
                    "channels": []
                },
                {
                    "id": "72",
                    "name": "MANUFACTURER_SPECIFIC",
                    "version": "1",
                    "nif": false,
                    "basic": false,
                    "secure": false,
                    "nonsecure": true,
                    "config": "",
                    "channels": []
                },
                {
                    "id": "80",
                    "name": "BATTERY",
                    "version": "1",
                    "nif": false,
                    "basic": false,
                    "secure": false,
                    "nonsecure": true,
                    "config": "",
                    "channels": []
                },
                {
                    "id": "85",
                    "name": "ASSOCIATION",
                    "version": "1",
                    "nif": false,
                    "basic": false,
                    "secure": false,
                    "nonsecure": false,
                    "config": "",
                    "channels": []
                },
                {
                    "id": "86",
                    "name": "VERSION",
                    "version": "1",
                    "nif": false,
                    "basic": false,
                    "secure": false,
                    "nonsecure": true,
                    "config": "",
                    "channels": []
                },
                {
                    "id": "8B",
                    "name": "TIME_PARAMETERS",
                    "version": "1",
                    "nif": false,
                    "basic": false,
                    "secure": false,
                    "nonsecure": false,
                    "config": "",
                    "channels": []
                },
                {
                    "id": "98",
                    "name": "SECURITY",
                    "version": "1",
                    "nif": false,
                    "basic": false,
                    "secure": false,
                    "nonsecure": true,
                    "config": "",
                    "channels": []
                }
            ]
        }
    ],
    "parameters": [],
    "associations": []
}